modelbridge/__init__.py
modelbridge/bridge.py
modelbridge/config_bridge.py
modelbridge/cache/__init__.py
modelbridge/cache/base.py
modelbridge/cache/decorators.py
modelbridge/cache/factory.py
modelbridge/cache/memory.py
modelbridge/cache/redis.py
modelbridge/config/__init__.py
modelbridge/config/loader.py
modelbridge/config/models.py
modelbridge/hooks/__init__.py
modelbridge/hooks/base.py
modelbridge/hooks/monitoring_hooks.py
modelbridge/middleware/__init__.py
modelbridge/middleware/base.py
modelbridge/middleware/request_middleware.py
modelbridge/monitoring/__init__.py
modelbridge/monitoring/alerts.py
modelbridge/monitoring/health.py
modelbridge/monitoring/metrics.py
modelbridge/monitoring/performance.py
modelbridge/plugins/__init__.py
modelbridge/plugins/base.py
modelbridge/plugins/routing_plugins.py
modelbridge/providers/__init__.py
modelbridge/providers/anthropic.py
modelbridge/providers/base.py
modelbridge/providers/google.py
modelbridge/providers/groq.py
modelbridge/providers/openai.py
modelbridge/ratelimit/__init__.py
modelbridge/ratelimit/algorithms.py
modelbridge/ratelimit/base.py
modelbridge/ratelimit/decorators.py
modelbridge/ratelimit/factory.py
modelbridge/ratelimit/memory.py
modelbridge/ratelimit/redis.py
modelbridge/routing/__init__.py
modelbridge/routing/enhanced_router.py
modelbridge/routing/performance_tracker.py
modelbridge/routing/quality_scorer.py
modelbridge/routing/routing_strategies.py
modelbridge/streaming/__init__.py
modelbridge/streaming/sse_handler.py
modelbridge/streaming/stream_manager.py
modelbridge/streaming/streaming_handler.py
modelbridge/streaming/websocket_handler.py
modelbridge/utils/__init__.py
modelbridge/utils/retry.py
modelbridge/utils/validation.py
modelbridge-1.0.2.dist-info/licenses/LICENSE
tests/__init__.py
tests/conftest.py
tests/test_anthropic_provider.py
tests/test_base_provider.py
tests/test_bridge_advanced.py
tests/test_bridge_basic.py
tests/test_cache_integration.py
tests/test_cache_system.py
tests/test_config_validation.py
tests/test_convenience_functions.py
modelbridge-1.0.2.dist-info/METADATA
modelbridge-1.0.2.dist-info/WHEEL
modelbridge-1.0.2.dist-info/top_level.txt
modelbridge-1.0.2.dist-info/RECORD
