Metadata-Version: 2.4
Name: modelbridge
Version: 1.0.2
Summary: Enterprise-Grade Multi-Provider LLM Gateway with Intelligent Routing
Home-page: https://github.com/code-mohanprakash/modelbridge
Author: Mohan Prakash
Author-email: Mohan Prakash <mohanprkash462@gmail.com>
License: MIT
Project-URL: Homepage, https://github.com/code-mohanprakash/modelbridge
Project-URL: Repository, https://github.com/code-mohanprakash/modelbridge
Project-URL: Issues, https://github.com/code-mohanprakash/modelbridge/issues
Keywords: llm,ai,gateway,routing,openai,anthropic,google,groq,multi-provider,load-balancing
Classifier: Development Status :: 4 - Beta
Classifier: Intended Audience :: Developers
Classifier: License :: OSI Approved :: MIT License
Classifier: Programming Language :: Python :: 3
Classifier: Programming Language :: Python :: 3.8
Classifier: Programming Language :: Python :: 3.9
Classifier: Programming Language :: Python :: 3.10
Classifier: Programming Language :: Python :: 3.11
Classifier: Topic :: Software Development :: Libraries :: Python Modules
Classifier: Topic :: Scientific/Engineering :: Artificial Intelligence
Requires-Python: >=3.8
License-File: LICENSE
Requires-Dist: aiohttp>=3.8.0
Requires-Dist: pydantic>=2.0.0
Requires-Dist: openai>=1.0.0
Requires-Dist: anthropic>=0.5.0
Requires-Dist: google-generativeai>=0.3.0
Requires-Dist: groq>=0.4.0
Requires-Dist: PyYAML>=6.0
Requires-Dist: python-dotenv>=1.0.0
Requires-Dist: typing-extensions>=4.5.0
Requires-Dist: psutil>=5.9.0
Requires-Dist: redis>=4.5.0
Provides-Extra: dev
Requires-Dist: pytest>=7.0.0; extra == "dev"
Requires-Dist: pytest-asyncio>=0.21.0; extra == "dev"
Requires-Dist: pytest-cov>=4.0.0; extra == "dev"
Requires-Dist: black>=23.0.0; extra == "dev"
Requires-Dist: isort>=5.12.0; extra == "dev"
Requires-Dist: flake8>=6.0.0; extra == "dev"
Requires-Dist: mypy>=1.0.0; extra == "dev"
Provides-Extra: ml
Requires-Dist: scikit-learn>=1.3.0; extra == "ml"
Requires-Dist: numpy>=1.24.0; extra == "ml"
Requires-Dist: pandas>=2.0.0; extra == "ml"
Dynamic: author
Dynamic: home-page
Dynamic: license-file
Dynamic: requires-python
